pysy/__init__.py
pysy/fluxlib/__init__.py
pysy/fluxlib/fluxnet.py
pysy/fluxlib/preproc/__init__.py
pysy/fluxlib/preproc/flux_read.py
pysy/fluxlib/preproc/standtob1.py
pysy/fluxlib/preproc/transcriptor.py
pysy/fluxlib/preproc/utilizes.py
pysy/scigee/__init__.py
pysy/scigee/canvas.py
pysy/scigee/gee_v0.2.x.py
pysy/scigee/geeface.py
pysy/scigeo/__init__.py
pysy/scigeo/geo.py
pysy/toolbox/__init__.py
pysy/toolbox/utils.py
pysy/toolbox/viz_params.py
pysy-0.0.34.dist-info/METADATA
pysy-0.0.34.dist-info/WHEEL
pysy-0.0.34.dist-info/top_level.txt
pysy-0.0.34.dist-info/RECORD
