Metadata-Version: 2.1
Name: pysy
Version: 0.0.34
Summary: For faster proccessing geofile
Home-page: https://github.com/soonyenju/pysy
Author: Songyan Zhu
Author-email: soonyenju@foxmail.com
License: MIT Licence
Keywords: easy geo warpper,atmospheric data,satellite data,flux
Platform: any
Requires-Dist: geopandas
Requires-Dist: rasterio
